{"version":1,"resource":"file:///home/eragon/repos/fluves/pyiotdataflow/src/pyiotdataflow/geoluxserver.py","entries":[{"id":"tj12.py","timestamp":1662021789265},{"id":"EnBS.py","timestamp":1662021919206},{"id":"oCDE.py","timestamp":1662021961877},{"id":"2bur.py","timestamp":1662022007637},{"id":"leeh.py","timestamp":1662022020661},{"id":"ibXq.py","timestamp":1662022107068},{"id":"vUlz.py","timestamp":1662023764087},{"id":"qYEU.py","timestamp":1662023809571},{"id":"uyCQ.py","timestamp":1662023973141},{"id":"VMjT.py","timestamp":1662023991668},{"id":"IU12.py","timestamp":1662024549720},{"id":"Mo2Z.py","timestamp":1662024753596},{"id":"h12d.py","timestamp":1662024876156},{"id":"mv0Q.py","timestamp":1662026686790},{"id":"CUvM.py","timestamp":1662026716331},{"id":"WwQm.py","timestamp":1662026783443},{"id":"doFH.py","timestamp":1662026816700},{"id":"TjFD.py","timestamp":1662027001567},{"id":"Cm7a.py","timestamp":1662027078330},{"id":"JQD8.py","timestamp":1662027119131},{"id":"iYCG.py","timestamp":1662027141472},{"id":"5H4S.py","timestamp":1662027183070},{"id":"aMFr.py","timestamp":1662027205103},{"id":"v6G2.py","timestamp":1662027233022}]}